{
    "KPackageStructure": "Plasma/LookAndFeel",
    "KPlugin": {
        "Authors": [
            {
                "Email": "l4k1987@gmail.com",
                "Name": "l4k1"
            }
        ],
        "Category": "Global Themes (Plasma 6)",
        "ServiceTypes": [
            "Plasma/LookAndFeel"
        ],
        "EnabledByDefault": true,
        "Name": "Gently-Dark-Global-6",
        "Description": "Gently-Dark Global Theme by l4k1",
        "Id": "Gently-Dark-Global-6",
        "Version": "1.2",
        "License": "GPLv3",
        "Website": "https://github.com/L4ki/Gently"
    },
    "X-KPackage-Dependencies": [
        "kns://window-decorations.knsrc/api.kde-look.org/2136787",
        "kns://window-decorations.knsrc/api.kde-look.org/2136785",
        "kns://colorschemes.knsrc/api.kde-look.org/1293162",
        "kns://icons.knsrc/api.kde-look.org/2136782",
        "kns://icons.knsrc/api.kde-look.org/2119129",
        "kns://icons.knsrc/api.kde-look.org/2136240",
        "kns://icons.knsrc/api.kde-look.org/1281798",
        "kns://plasma-themes.knsrc/api.kde-look.org/1293160",
        "kns://sddmtheme.knsrc/api.kde-look.org/2156566",
        "kns://wallpaper.knsrc/api.kde-look.org/2110165",
        "kns://wallpaper.knsrc/api.kde-look.org/1365304",
        "kns://wallpaper.knsrc/api.kde-look.org/2156565",
        "kns://wallpaper.knsrc/api.kde-look.org/1365306"
    ]
}
